qsimov_cloud_client/__init__.py
qsimov_cloud_client/client.py
qsimov_cloud_client/utils.py
qsimov_cloud_client-0.0.3.dist-info/METADATA
qsimov_cloud_client-0.0.3.dist-info/WHEEL
qsimov_cloud_client-0.0.3.dist-info/licenses/LICENSE
qsimov_cloud_client-0.0.3.dist-info/RECORD
