Metadata-Version: 2.1
Name: qsimov-cloud-client
Version: 0.0.3
Summary: The package to connect with the QSimov cloud services
Project-URL: Homepage, https://github.com/QSimovTech/qsimov-cloud-client
Project-URL: Bug Tracker, https://github.com/QSimovTech/qsimov-cloud-client/issues
Author-email: "QSimov Quantum Computing S.L." <tech@qsimov.com>
License-File: LICENSE
Classifier: License :: OSI Approved :: MIT License
Classifier: Operating System :: OS Independent
Classifier: Programming Language :: Python :: 3
Requires-Python: >=3.7
